gmux/__init__.py
gmux/__main__.py
gmux/bin/gmux
gmux-0.1.1.dist-info/METADATA
gmux-0.1.1.dist-info/WHEEL
gmux-0.1.1.dist-info/entry_points.txt
gmux-0.1.1.dist-info/top_level.txt
gmux-0.1.1.dist-info/RECORD
