Metadata-Version: 2.4
Name: gmux
Version: 0.1.1
Summary: Terminal UI to switch between git working directories and launch editors
Author: Lawrence Chen
License: MIT
Project-URL: Homepage, https://github.com/lawrencechen/gmux
Keywords: git,tui,workspace,cli
Classifier: Development Status :: 4 - Beta
Classifier: Intended Audience :: Developers
Classifier: License :: OSI Approved :: MIT License
Classifier: Programming Language :: Python
Classifier: Programming Language :: Python :: 3
Classifier: Programming Language :: Python :: 3.8
Classifier: Programming Language :: Python :: 3.9
Classifier: Programming Language :: Python :: 3.10
Classifier: Programming Language :: Python :: 3.11
Classifier: Programming Language :: Python :: 3.12
Classifier: Environment :: Console
Requires-Python: >=3.8
